Metadata-Version: 2.1
Name: cometml-api
Version: 0.1
Summary: Python bindings for the CometML REST API.
Home-page: https://github.com/neighthan/cometml_api
Author: Nathan Hunt
Author-email: neighthan.hunt@gmail.com
License: UNKNOWN
Platform: UNKNOWN
Classifier: Programming Language :: Python :: 3
Classifier: License :: OSI Approved :: MIT License
Classifier: Operating System :: OS Independent
